README.md
ansito/__init__.py
ansito/__main__.py
ansito/cli.py
pyproject.toml
ansito-0.1.0.dist-info/entry_points.txt
ansito-0.1.0.dist-info/LICENSE
ansito-0.1.0.dist-info/WHEEL
ansito-0.1.0.dist-info/METADATA
ansito-0.1.0.dist-info/RECORD
