Metadata-Version: 2.1
Name: ansito
Version: 0.1.0
Summary: Translate ANSI codes to any other format.
Home-page: https://github.com/pawamoy/ansito
License: UNKNOWN
Author: Timothée Mazzucotelli
Author-email: pawamoy@pm.me
Requires-Python: >=3.6,<4.0
Classifier: Programming Language :: Python :: 3
Classifier: Programming Language :: Python :: 3.6
Classifier: Programming Language :: Python :: 3.7
Project-URL: Repository, https://github.com/pawamoy/ansito
